Metadata-Version: 1.1
Name: pyfft
Version: 0.3.8
Summary: FFT library for PyCuda and PyOpenCL
Home-page: http://github.com/Manticore/pyfft
Author: Bogdan Opanchuk
Author-email: mantihor@gmail.com
License: UNKNOWN
Platform: UNKNOWN
Classifier: Development Status :: 4 - Beta
Classifier: Intended Audience :: Developers
Classifier: License :: OSI Approved :: MIT License
Classifier: Operating System :: OS Independent
Classifier: Programming Language :: Python :: 2
Classifier: Topic :: Scientific/Engineering :: Mathematics
Requires: mako
Requires: numpy
Provides: pyfft
